aer/__init__.py
aer/cli/__init__.py
aer/cli/cli.py
aer-0.2.0.dist-info/entry_points.txt
aer-0.2.0.dist-info/LICENSE
aer-0.2.0.dist-info/WHEEL
aer-0.2.0.dist-info/METADATA
aer-0.2.0.dist-info/RECORD
