Metadata-Version: 2.1
Name: aer
Version: 0.2.0
Summary: A CLI helper for using EMR on AWS
Home-page: https://github.com/eganjs/aer
License: MIT
Author: Joseph Egan
Author-email: joseph.s.egan@gmail.com
Requires-Python: >=3.6,<4.0
Classifier: License :: OSI Approved :: MIT License
Classifier: Programming Language :: Python :: 3
Classifier: Programming Language :: Python :: 3.6
Classifier: Programming Language :: Python :: 3.7
Classifier: Programming Language :: Python :: 3.8
Requires-Dist: click (>=7.1.2,<8.0.0)
Project-URL: Repository, https://github.com/eganjs/aer
